eshqol/__init__.py
eshqol-0.0.3.dist-info/METADATA
eshqol-0.0.3.dist-info/WHEEL
eshqol-0.0.3.dist-info/top_level.txt
eshqol-0.0.3.dist-info/RECORD
