Metadata-Version: 2.1
Name: eshqol
Version: 0.0.3
Summary: UNKNOWN
Home-page: UNKNOWN
Author: Eshqol Development
Author-email: eshqoldev@gmail.com
License: MIT
Platform: UNKNOWN
Classifier: Programming Language :: Python :: 3
Classifier: License :: OSI Approved :: MIT License
Classifier: Operating System :: OS Independent
Requires-Dist: numpy
Requires-Dist: pyautogui
Requires-Dist: mouse
Requires-Dist: pyclick
